aiokafkadaemon/__init__.py
aiokafkadaemon/advanced.py
aiokafkadaemon/daemon.py
aiokafkadaemon/errors.py
aiokafkadaemon/worker.py
aio_kafka_daemon-1.0.11.dist-info/LICENSE
aio_kafka_daemon-1.0.11.dist-info/METADATA
aio_kafka_daemon-1.0.11.dist-info/WHEEL
aio_kafka_daemon-1.0.11.dist-info/entry_points.txt
aio_kafka_daemon-1.0.11.dist-info/top_level.txt
aio_kafka_daemon-1.0.11.dist-info/RECORD
